reranking/__init__.py
reranking/algs.py
reranking/metrics.py
reranking/reranker.py
tests/__init__.py
tests/test_algs.py
tests/test_metrics.py
tests/test_reranker.py
reranking-0.3.6.dist-info/LICENSE
reranking-0.3.6.dist-info/METADATA
reranking-0.3.6.dist-info/WHEEL
reranking-0.3.6.dist-info/top_level.txt
reranking-0.3.6.dist-info/RECORD
