Metadata-Version: 2.1
Name: reranking
Version: 0.3.6
Summary: UNKNOWN
Home-page: https://github.com/yuanlonghao/reranking
Author: Longhao Yuan
Author-email: yuanlonghao1013@gmail.com
License: UNKNOWN
Platform: UNKNOWN
Requires-Python: >=3.6
License-File: LICENSE
